narsil/__init__.py
narsil/__main__.py
narsil/fish/__init__.py
narsil/fish/datasets.py
narsil/segmentation/__init__.py
narsil/segmentation/datasets.py
narsil/segmentation/liverun.py
narsil/segmentation/modelDev.py
narsil/segmentation/network.py
narsil/segmentation/run.py
narsil/tracking/__init__.py
narsil/tracking/liverun.py
narsil/tracking/run.py
narsil/tracking/siamese/__init__.py
narsil/tracking/siamese/datasets.py
narsil/tracking/siamese/generateTrackingData.py
narsil/tracking/siamese/modelDev.py
narsil/tracking/siamese/network.py
narsil/tracking/siamese/trainDatasets.py
narsil/utils/__init__.py
narsil/utils/fluorOperations.py
narsil/utils/growth.py
narsil/utils/losses.py
narsil/utils/transforms.py
narsil-0.1.0.dist-info/DESCRIPTION.rst
narsil-0.1.0.dist-info/METADATA
narsil-0.1.0.dist-info/RECORD
narsil-0.1.0.dist-info/WHEEL
narsil-0.1.0.dist-info/metadata.json
narsil-0.1.0.dist-info/top_level.txt
