Metadata-Version: 2.0
Name: narsil
Version: 0.1.0
Summary: The package to work with microscopy data of prokaryotic cells
Home-page: https://github.com/karempudi/narsil
Author: Praneeth Karempudi
Author-email: praneeth.karempudi@gmail.com
License: LICENSE.txt
Platform: UNKNOWN
Requires-Dist: numpy
Requires-Dist: torch
Requires-Dist: torchvision
Requires-Dist: scikit-image
Requires-Dist: scipy
Requires-Dist: matplotlib
Requires-Dist: wxPython
